pypolycontain/__init__.py
pypolycontain/_temp.py
pypolycontain/containment.py
pypolycontain/conversions.py
pypolycontain/objects.py
pypolycontain/operations.py
pypolycontain/visualize.py
pypolycontain-2.0.dist-info/METADATA
pypolycontain-2.0.dist-info/WHEEL
pypolycontain-2.0.dist-info/top_level.txt
pypolycontain-2.0.dist-info/RECORD
