Metadata-Version: 2.1
Name: pypolycontain
Version: 2.0
Summary: A python package for polytopic objects, operations, and containment encodings
Home-page: https://github.com/sadraddini/pypolycontain
Author: Sadra Sadraddini
Author-email: sadra@mit.edu
License: MIT
Platform: UNKNOWN
